{"0810200":{"prefecture":"北海道","city":"河東郡鹿追町","area":""},"0810212":{"prefecture":"北海道","city":"河東郡鹿追町","area":"泉町"},"0810342":{"prefecture":"北海道","city":"河東郡鹿追町","area":"瓜幕東"},"0810341":{"prefecture":"北海道","city":"河東郡鹿追町","area":"瓜幕西"},"0810343":{"prefecture":"北海道","city":"河東郡鹿追町","area":"瓜幕南"},"0810225":{"prefecture":"北海道","city":"河東郡鹿追町","area":"柏ケ丘"},"0810218":{"prefecture":"北海道","city":"河東郡鹿追町","area":"上然別西"},"0810226":{"prefecture":"北海道","city":"河東郡鹿追町","area":"上幌内"},"0810344":{"prefecture":"北海道","city":"河東郡鹿追町","area":"北瓜幕"},"0810214":{"prefecture":"北海道","city":"河東郡鹿追町","area":"北鹿追北"},"0810202":{"prefecture":"北海道","city":"河東郡鹿追町","area":"北町"},"0810221":{"prefecture":"北海道","city":"河東郡鹿追町","area":"栄町"},"0810204":{"prefecture":"北海道","city":"河東郡鹿追町","area":"笹川北"},"0810217":{"prefecture":"北海道","city":"河東郡鹿追町","area":"鹿追基線"},"0810215":{"prefecture":"北海道","city":"河東郡鹿追町","area":"鹿追南"},"0810216":{"prefecture":"北海道","city":"河東郡鹿追町","area":"鹿追北"},"0810201":{"prefecture":"北海道","city":"河東郡鹿追町","area":"新町"},"0810345":{"prefecture":"北海道","city":"河東郡鹿追町","area":"中瓜幕西"},"0810211":{"prefecture":"北海道","city":"河東郡鹿追町","area":"仲町"},"0810205":{"prefecture":"北海道","city":"河東郡鹿追町","area":"西笹川"},"0810213":{"prefecture":"北海道","city":"河東郡鹿追町","area":"西町"},"0810346":{"prefecture":"北海道","city":"河東郡鹿追町","area":"東瓜幕西"},"0810222":{"prefecture":"北海道","city":"河東郡鹿追町","area":"東町"},"0810228":{"prefecture":"北海道","city":"河東郡鹿追町","area":"美蔓西"},"0810227":{"prefecture":"北海道","city":"河東郡鹿追町","area":"幌内西"},"0810203":{"prefecture":"北海道","city":"河東郡鹿追町","area":"緑町"},"0810223":{"prefecture":"北海道","city":"河東郡鹿追町","area":"南町"},"0810224":{"prefecture":"北海道","city":"河東郡鹿追町","area":"元町"},"0810000":{"prefecture":"北海道","city":"上川郡新得町","area":""},"0810035":{"prefecture":"北海道","city":"上川郡新得町","area":"上佐幌"},"0810154":{"prefecture":"北海道","city":"上川郡新得町","area":"屈足"},"0810151":{"prefecture":"北海道","city":"上川郡新得町","area":"屈足旭町"},"0810152":{"prefecture":"北海道","city":"上川郡新得町","area":"屈足旭町東"},"0810161":{"prefecture":"北海道","city":"上川郡新得町","area":"屈足柏町"},"0810162":{"prefecture":"北海道","city":"上川郡新得町","area":"屈足柏町東"},"0810155":{"prefecture":"北海道","city":"上川郡新得町","area":"屈足幸町"},"0810156":{"prefecture":"北海道","city":"上川郡新得町","area":"屈足幸町西"},"0810163":{"prefecture":"北海道","city":"上川郡新得町","area":"屈足緑町"},"0810164":{"prefecture":"北海道","city":"上川郡新得町","area":"屈足緑町西"},"0810153":{"prefecture":"北海道","city":"上川郡新得町","area":"屈足南町"},"0810006":{"prefecture":"北海道","city":"上川郡新得町","area":"栄町"},"0810036":{"prefecture":"北海道","city":"上川郡新得町","area":"下佐幌"},"0810038":{"prefecture":"北海道","city":"上川郡新得町","area":"新得"},"0810037":{"prefecture":"北海道","city":"上川郡新得町","area":"拓鉄"},"0810039":{"prefecture":"北海道","city":"上川郡新得町","area":"新内"},"0810031":{"prefecture":"北海道","city":"上川郡新得町","area":"西一条南"},"0810021":{"prefecture":"北海道","city":"上川郡新得町","area":"西一条北"},"0810032":{"prefecture":"北海道","city":"上川郡新得町","area":"西二条南"},"0810022":{"prefecture":"北海道","city":"上川郡新得町","area":"西二条北"},"0810033":{"prefecture":"北海道","city":"上川郡新得町","area":"西三条南"},"0810023":{"prefecture":"北海道","city":"上川郡新得町","area":"西三条北"},"0810034":{"prefecture":"北海道","city":"上川郡新得町","area":"西四条南"},"0810008":{"prefecture":"北海道","city":"上川郡新得町","area":"本通南"},"0810005":{"prefecture":"北海道","city":"上川郡新得町","area":"本通北"},"0810007":{"prefecture":"北海道","city":"上川郡新得町","area":"元町"},"0810011":{"prefecture":"北海道","city":"上川郡新得町","area":"一条南"},"0810001":{"prefecture":"北海道","city":"上川郡新得町","area":"一条北"},"0810012":{"prefecture":"北海道","city":"上川郡新得町","area":"二条南"},"0810002":{"prefecture":"北海道","city":"上川郡新得町","area":"二条北"},"0810013":{"prefecture":"北海道","city":"上川郡新得町","area":"三条南"},"0810003":{"prefecture":"北海道","city":"上川郡新得町","area":"三条北"},"0810014":{"prefecture":"北海道","city":"上川郡新得町","area":"四条南"},"0810015":{"prefecture":"北海道","city":"上川郡新得町","area":"五条南"}}