{"5210000":[{"prefecture":"滋賀県","city":"米原市","area":""}],"5210001":[{"prefecture":"滋賀県","city":"米原市","area":"朝妻筑摩"}],"5210002":[{"prefecture":"滋賀県","city":"米原市","area":"上多良"}],"5210003":[{"prefecture":"滋賀県","city":"米原市","area":"入江"}],"5210004":[{"prefecture":"滋賀県","city":"米原市","area":"磯"}],"5210011":[{"prefecture":"滋賀県","city":"米原市","area":"中多良"}],"5210012":[{"prefecture":"滋賀県","city":"米原市","area":"米原"}],"5210013":[{"prefecture":"滋賀県","city":"米原市","area":"梅ケ原"}],"5210014":[{"prefecture":"滋賀県","city":"米原市","area":"梅ケ原栄"}],"5210015":[{"prefecture":"滋賀県","city":"米原市","area":"米原西"}],"5210016":[{"prefecture":"滋賀県","city":"米原市","area":"下多良"}],"5210021":[{"prefecture":"滋賀県","city":"米原市","area":"河南"}],"5210022":[{"prefecture":"滋賀県","city":"米原市","area":"樋口"}],"5210023":[{"prefecture":"滋賀県","city":"米原市","area":"三吉"}],"5210024":[{"prefecture":"滋賀県","city":"米原市","area":"西坂"}],"5210025":[{"prefecture":"滋賀県","city":"米原市","area":"番場"}],"5210031":[{"prefecture":"滋賀県","city":"米原市","area":"一色"}],"5210032":[{"prefecture":"滋賀県","city":"米原市","area":"枝折"}],"5210033":[{"prefecture":"滋賀県","city":"米原市","area":"上丹生"}],"5210034":[{"prefecture":"滋賀県","city":"米原市","area":"下丹生"}],"5210035":[{"prefecture":"滋賀県","city":"米原市","area":"醒井"}],"5210061":[{"prefecture":"滋賀県","city":"米原市","area":"長沢"}],"5210062":[{"prefecture":"滋賀県","city":"米原市","area":"宇賀野"}],"5210063":[{"prefecture":"滋賀県","city":"米原市","area":"飯"}],"5210064":[{"prefecture":"滋賀県","city":"米原市","area":"世継"}],"5210071":[{"prefecture":"滋賀県","city":"米原市","area":"舟崎"}],"5210072":[{"prefecture":"滋賀県","city":"米原市","area":"顔戸"}],"5210073":[{"prefecture":"滋賀県","city":"米原市","area":"箕浦"}],"5210074":[{"prefecture":"滋賀県","city":"米原市","area":"高溝"}],"5210081":[{"prefecture":"滋賀県","city":"米原市","area":"多和田"}],"5210082":[{"prefecture":"滋賀県","city":"米原市","area":"能登瀬"}],"5210083":[{"prefecture":"滋賀県","city":"米原市","area":"新庄"}],"5210084":[{"prefecture":"滋賀県","city":"米原市","area":"日光寺"}],"5210091":[{"prefecture":"滋賀県","city":"米原市","area":"岩脇"}],"5210092":[{"prefecture":"滋賀県","city":"米原市","area":"西円寺"}],"5210093":[{"prefecture":"滋賀県","city":"米原市","area":"寺倉"}],"5210201":[{"prefecture":"滋賀県","city":"米原市","area":"長久寺"}],"5210202":[{"prefecture":"滋賀県","city":"米原市","area":"柏原"}],"5210203":[{"prefecture":"滋賀県","city":"米原市","area":"清滝"}],"5210211":[{"prefecture":"滋賀県","city":"米原市","area":"梓河内"}],"5210212":[{"prefecture":"滋賀県","city":"米原市","area":"本郷"}],"5210213":[{"prefecture":"滋賀県","city":"米原市","area":"堂谷"}],"5210214":[{"prefecture":"滋賀県","city":"米原市","area":"大鹿"}],"5210215":[{"prefecture":"滋賀県","city":"米原市","area":"山室"}],"5210216":[{"prefecture":"滋賀県","city":"米原市","area":"菅江"}],"5210217":[{"prefecture":"滋賀県","city":"米原市","area":"北方"}],"5210218":[{"prefecture":"滋賀県","city":"米原市","area":"志賀谷"}],"5210219":[{"prefecture":"滋賀県","city":"米原市","area":"加勢野"}],"5210221":[{"prefecture":"滋賀県","city":"米原市","area":"池下"}],"5210222":[{"prefecture":"滋賀県","city":"米原市","area":"天満"}],"5210223":[{"prefecture":"滋賀県","city":"米原市","area":"本市場"}],"5210224":[{"prefecture":"滋賀県","city":"米原市","area":"夫馬"}],"5210225":[{"prefecture":"滋賀県","city":"米原市","area":"市場"}],"5210226":[{"prefecture":"滋賀県","city":"米原市","area":"朝日"}],"5210227":[{"prefecture":"滋賀県","city":"米原市","area":"烏脇"}],"5210231":[{"prefecture":"滋賀県","city":"米原市","area":"村居田"}],"5210232":[{"prefecture":"滋賀県","city":"米原市","area":"坂口"}],"5210233":[{"prefecture":"滋賀県","city":"米原市","area":"野一色"}],"5210234":[{"prefecture":"滋賀県","city":"米原市","area":"井之口"}],"5210235":[{"prefecture":"滋賀県","city":"米原市","area":"小田"}],"5210236":[{"prefecture":"滋賀県","city":"米原市","area":"間田"}],"5210241":[{"prefecture":"滋賀県","city":"米原市","area":"西山"}],"5210242":[{"prefecture":"滋賀県","city":"米原市","area":"長岡"}],"5210243":[{"prefecture":"滋賀県","city":"米原市","area":"万願寺"}],"5210244":[{"prefecture":"滋賀県","city":"米原市","area":"大野木"}],"5210245":[{"prefecture":"滋賀県","city":"米原市","area":"須川"}],"5210301":[{"prefecture":"滋賀県","city":"米原市","area":"甲津原"}],"5210302":[{"prefecture":"滋賀県","city":"米原市","area":"曲谷"}],"5210303":[{"prefecture":"滋賀県","city":"米原市","area":"甲賀"}],"5210304":[{"prefecture":"滋賀県","city":"米原市","area":"吉槻"}],"5210305":[{"prefecture":"滋賀県","city":"米原市","area":"上板並"}],"5210306":[{"prefecture":"滋賀県","city":"米原市","area":"下板並"}],"5210307":[{"prefecture":"滋賀県","city":"米原市","area":"大久保"}],"5210308":[{"prefecture":"滋賀県","city":"米原市","area":"小泉"}],"5210311":[{"prefecture":"滋賀県","city":"米原市","area":"伊吹"}],"5210312":[{"prefecture":"滋賀県","city":"米原市","area":"上野"}],"5210313":[{"prefecture":"滋賀県","city":"米原市","area":"弥高"}],"5210314":[{"prefecture":"滋賀県","city":"米原市","area":"春照"}],"5210321":[{"prefecture":"滋賀県","city":"米原市","area":"高番"}],"5210322":[{"prefecture":"滋賀県","city":"米原市","area":"杉沢"}],"5210323":[{"prefecture":"滋賀県","city":"米原市","area":"村木"}],"5210324":[{"prefecture":"滋賀県","city":"米原市","area":"大清水"}],"5210325":[{"prefecture":"滋賀県","city":"米原市","area":"藤川"}],"5210326":[{"prefecture":"滋賀県","city":"米原市","area":"寺林"}],"5210327":[{"prefecture":"滋賀県","city":"米原市","area":"上平寺"}],"5211101":[{"prefecture":"滋賀県","city":"彦根市","area":"石寺町"}],"5211102":[{"prefecture":"滋賀県","city":"彦根市","area":"下岡部町"}],"5211103":[{"prefecture":"滋賀県","city":"彦根市","area":"上岡部町"}],"5211104":[{"prefecture":"滋賀県","city":"彦根市","area":"出路町"}],"5211105":[{"prefecture":"滋賀県","city":"彦根市","area":"田原町"}],"5211111":[{"prefecture":"滋賀県","city":"彦根市","area":"稲里町"}],"5211112":[{"prefecture":"滋賀県","city":"彦根市","area":"金沢町"}],"5211113":[{"prefecture":"滋賀県","city":"彦根市","area":"稲部町"}],"5211114":[{"prefecture":"滋賀県","city":"彦根市","area":"彦富町"}],"5211115":[{"prefecture":"滋賀県","city":"彦根市","area":"金田町"}],"5211121":[{"prefecture":"滋賀県","city":"彦根市","area":"海瀬町"}],"5211122":[{"prefecture":"滋賀県","city":"彦根市","area":"三津町"}],"5211123":[{"prefecture":"滋賀県","city":"彦根市","area":"肥田町"}],"5211124":[{"prefecture":"滋賀県","city":"彦根市","area":"野良田町"}],"5211125":[{"prefecture":"滋賀県","city":"彦根市","area":"稲枝町"}],"5211126":[{"prefecture":"滋賀県","city":"彦根市","area":"服部町"}],"5211131":[{"prefecture":"滋賀県","city":"彦根市","area":"上稲葉町"}],"5211132":[{"prefecture":"滋賀県","city":"彦根市","area":"下稲葉町"}],"5211133":[{"prefecture":"滋賀県","city":"彦根市","area":"本庄町"}],"5211134":[{"prefecture":"滋賀県","city":"彦根市","area":"田附町"}],"5211135":[{"prefecture":"滋賀県","city":"彦根市","area":"新海町"}],"5211136":[{"prefecture":"滋賀県","city":"彦根市","area":"新海浜"}],"5211141":[{"prefecture":"滋賀県","city":"彦根市","area":"甲崎町"}],"5211142":[{"prefecture":"滋賀県","city":"彦根市","area":"下西川町"}],"5211143":[{"prefecture":"滋賀県","city":"彦根市","area":"上西川町"}],"5211144":[{"prefecture":"滋賀県","city":"彦根市","area":"普光寺町"}],"5211145":[{"prefecture":"滋賀県","city":"彦根市","area":"南三ツ谷町"}],"5211146":[{"prefecture":"滋賀県","city":"彦根市","area":"柳川町"}],"5211147":[{"prefecture":"滋賀県","city":"彦根市","area":"薩摩町"}],"5211201":[{"prefecture":"滋賀県","city":"東近江市","area":"新宮町"}],"5211202":[{"prefecture":"滋賀県","city":"東近江市","area":"阿弥陀堂町"}],"5211203":[{"prefecture":"滋賀県","city":"東近江市","area":"川南町"}],"5211204":[{"prefecture":"滋賀県","city":"東近江市","area":"小川町"}],"5211205":[{"prefecture":"滋賀県","city":"東近江市","area":"躰光寺町"}],"5211211":[{"prefecture":"滋賀県","city":"東近江市","area":"今町"}],"5211212":[{"prefecture":"滋賀県","city":"東近江市","area":"種町"}],"5211213":[{"prefecture":"滋賀県","city":"東近江市","area":"神郷町"}],"5211214":[{"prefecture":"滋賀県","city":"東近江市","area":"長勝寺町"}],"5211215":[{"prefecture":"滋賀県","city":"東近江市","area":"佐生町"}],"5211221":[{"prefecture":"滋賀県","city":"東近江市","area":"垣見町"}],"5211222":[{"prefecture":"滋賀県","city":"東近江市","area":"佐野町"}],"5211223":[{"prefecture":"滋賀県","city":"東近江市","area":"猪子町"}],"5211224":[{"prefecture":"滋賀県","city":"東近江市","area":"林町"}],"5211225":[{"prefecture":"滋賀県","city":"東近江市","area":"山路町"}],"5211231":[{"prefecture":"滋賀県","city":"東近江市","area":"能登川町"}],"5211232":[{"prefecture":"滋賀県","city":"東近江市","area":"北須田町"}],"5211233":[{"prefecture":"滋賀県","city":"東近江市","area":"南須田町"}],"5211234":[{"prefecture":"滋賀県","city":"東近江市","area":"きぬがさ町"}],"5211235":[{"prefecture":"滋賀県","city":"東近江市","area":"伊庭町"}],"5211241":[{"prefecture":"滋賀県","city":"東近江市","area":"乙女浜町"}],"5211242":[{"prefecture":"滋賀県","city":"東近江市","area":"福堂町"}],"5211243":[{"prefecture":"滋賀県","city":"東近江市","area":"栗見新田町"}],"5211244":[{"prefecture":"滋賀県","city":"東近江市","area":"大中町"}],"5211245":[{"prefecture":"滋賀県","city":"東近江市","area":"栗見出在家町"}],"5211301":[{"prefecture":"滋賀県","city":"近江八幡市","area":"安土町大中"}],"5211311":[{"prefecture":"滋賀県","city":"近江八幡市","area":"安土町下豊浦"}],"5211321":[{"prefecture":"滋賀県","city":"近江八幡市","area":"安土町桑実寺"}],"5211322":[{"prefecture":"滋賀県","city":"近江八幡市","area":"安土町宮津"}],"5211331":[{"prefecture":"滋賀県","city":"近江八幡市","area":"安土町石寺"}],"5211332":[{"prefecture":"滋賀県","city":"近江八幡市","area":"安土町東老蘇"}],"5211333":[{"prefecture":"滋賀県","city":"近江八幡市","area":"安土町内野"}],"5211334":[{"prefecture":"滋賀県","city":"近江八幡市","area":"安土町西老蘇"}],"5211341":[{"prefecture":"滋賀県","city":"近江八幡市","area":"安土町上豊浦"}],"5211342":[{"prefecture":"滋賀県","city":"近江八幡市","area":"安土町上出"}],"5211343":[{"prefecture":"滋賀県","city":"近江八幡市","area":"安土町小中"}],"5211344":[{"prefecture":"滋賀県","city":"近江八幡市","area":"安土町中屋"}],"5211345":[{"prefecture":"滋賀県","city":"近江八幡市","area":"安土町慈恩寺"}],"5211346":[{"prefecture":"滋賀県","city":"近江八幡市","area":"安土町香庄"}],"5211351":[{"prefecture":"滋賀県","city":"近江八幡市","area":"安土町常楽寺"}]}