{"0170000":[{"prefecture":"秋田県","city":"大館市","area":""}],"0170806":[{"prefecture":"秋田県","city":"大館市","area":"相染沢中岱"}],"0170831":[{"prefecture":"秋田県","city":"大館市","area":"青葉町"}],"0170854":[{"prefecture":"秋田県","city":"大館市","area":"赤石"}],"0170816":[{"prefecture":"秋田県","city":"大館市","area":"赤館"}],"0170814":[{"prefecture":"秋田県","city":"大館市","area":"赤館町"}],"0170011":[{"prefecture":"秋田県","city":"大館市","area":"商人留"}],"0170025":[{"prefecture":"秋田県","city":"大館市","area":"芦田子"}],"0170023":[{"prefecture":"秋田県","city":"大館市","area":"東"}],"0170043":[{"prefecture":"秋田県","city":"大館市","area":"有浦"}],"0170836":[{"prefecture":"秋田県","city":"大館市","area":"池内"}],"0170834":[{"prefecture":"秋田県","city":"大館市","area":"池内道上"}],"0170832":[{"prefecture":"秋田県","city":"大館市","area":"池内道下"}],"0170845":[{"prefecture":"秋田県","city":"大館市","area":"泉町"}],"0170053":[{"prefecture":"秋田県","city":"大館市","area":"板子石境"}],"0170853":[{"prefecture":"秋田県","city":"大館市","area":"板沢"}],"0170825":[{"prefecture":"秋田県","city":"大館市","area":"一心院南"}],"0170801":[{"prefecture":"秋田県","city":"大館市","area":"一本杉"}],"0170857":[{"prefecture":"秋田県","city":"大館市","area":"出川"}],"0170894":[{"prefecture":"秋田県","city":"大館市","area":"裏町"}],"0170817":[{"prefecture":"秋田県","city":"大館市","area":"上町"}],"0170837":[{"prefecture":"秋田県","city":"大館市","area":"餌釣"}],"0170805":[{"prefecture":"秋田県","city":"大館市","area":"扇田道下"}],"0170024":[{"prefecture":"秋田県","city":"大館市","area":"大茂内"}],"0170041":[{"prefecture":"秋田県","city":"大館市","area":"大田面"}],"0170896":[{"prefecture":"秋田県","city":"大館市","area":"大館"}],"0170851":[{"prefecture":"秋田県","city":"大館市","area":"大披"}],"0170841":[{"prefecture":"秋田県","city":"大館市","area":"大町"}],"0170044":[{"prefecture":"秋田県","city":"大館市","area":"御成町"}],"0170004":[{"prefecture":"秋田県","city":"大館市","area":"粕田"}],"0170892":[{"prefecture":"秋田県","city":"大館市","area":"片町"}],"0170871":[{"prefecture":"秋田県","city":"大館市","area":"片山"}],"0170872":[{"prefecture":"秋田県","city":"大館市","area":"片山町"}],"0170812":[{"prefecture":"秋田県","city":"大館市","area":"金坂"}],"0170813":[{"prefecture":"秋田県","city":"大館市","area":"金坂後"}],"0170031":[{"prefecture":"秋田県","city":"大館市","area":"上代野"}],"0170804":[{"prefecture":"秋田県","city":"大館市","area":"柄沢"}],"0170878":[{"prefecture":"秋田県","city":"大館市","area":"川口"}],"0170042":[{"prefecture":"秋田県","city":"大館市","area":"観音堂"}],"0170866":[{"prefecture":"秋田県","city":"大館市","area":"北神明町"}],"0170893":[{"prefecture":"秋田県","city":"大館市","area":"桂城"}],"0170014":[{"prefecture":"秋田県","city":"大館市","area":"小釈迦内道上"}],"0170015":[{"prefecture":"秋田県","city":"大館市","area":"小釈迦内道下"}],"0170861":[{"prefecture":"秋田県","city":"大館市","area":"小館町"}],"0170835":[{"prefecture":"秋田県","city":"大館市","area":"小館花"}],"0170852":[{"prefecture":"秋田県","city":"大館市","area":"小袴"}],"0170847":[{"prefecture":"秋田県","city":"大館市","area":"幸町"}],"0170821":[{"prefecture":"秋田県","city":"大館市","area":"桜町"}],"0170822":[{"prefecture":"秋田県","city":"大館市","area":"桜町南"}],"0170897":[{"prefecture":"秋田県","city":"大館市","area":"三ノ丸"}],"0170022":[{"prefecture":"秋田県","city":"大館市","area":"茂内"}],"0170046":[{"prefecture":"秋田県","city":"大館市","area":"清水"}],"0170037":[{"prefecture":"秋田県","city":"大館市","area":"清水堰合"}],"0170034":[{"prefecture":"秋田県","city":"大館市","area":"下代野"}],"0170033":[{"prefecture":"秋田県","city":"大館市","area":"下綱"}],"0170012":[{"prefecture":"秋田県","city":"大館市","area":"釈迦内"}],"0170865":[{"prefecture":"秋田県","city":"大館市","area":"城西町"}],"0170002":[{"prefecture":"秋田県","city":"大館市","area":"白沢"}],"0170844":[{"prefecture":"秋田県","city":"大館市","area":"新町"}],"0170887":[{"prefecture":"秋田県","city":"大館市","area":"水門町"}],"0170888":[{"prefecture":"秋田県","city":"大館市","area":"水門前"}],"0170875":[{"prefecture":"秋田県","city":"大館市","area":"住吉町"}],"0170833":[{"prefecture":"秋田県","city":"大館市","area":"象ケ鼻"}],"0170035":[{"prefecture":"秋田県","city":"大館市","area":"代野"}],"0170886":[{"prefecture":"秋田県","city":"大館市","area":"館下"}],"0170877":[{"prefecture":"秋田県","city":"大館市","area":"立花"}],"0170882":[{"prefecture":"秋田県","city":"大館市","area":"鉄砲場"}],"0170846":[{"prefecture":"秋田県","city":"大館市","area":"常盤木町"}],"0170884":[{"prefecture":"秋田県","city":"大館市","area":"土飛山下"}],"0170867":[{"prefecture":"秋田県","city":"大館市","area":"中神明町"}],"0170891":[{"prefecture":"秋田県","city":"大館市","area":"中城"}],"0170843":[{"prefecture":"秋田県","city":"大館市","area":"中町"}],"0170045":[{"prefecture":"秋田県","city":"大館市","area":"中道"}],"0170839":[{"prefecture":"秋田県","city":"大館市","area":"中山"}],"0170881":[{"prefecture":"秋田県","city":"大館市","area":"長木川南"}],"0170895":[{"prefecture":"秋田県","city":"大館市","area":"長倉"}],"0170802":[{"prefecture":"秋田県","city":"大館市","area":"長根山下"}],"0170001":[{"prefecture":"秋田県","city":"大館市","area":"長走"}],"0170824":[{"prefecture":"秋田県","city":"大館市","area":"七曲岱"}],"0170032":[{"prefecture":"秋田県","city":"大館市","area":"新綱"}],"0170036":[{"prefecture":"秋田県","city":"大館市","area":"二本杉後"}],"0170055":[{"prefecture":"秋田県","city":"大館市","area":"沼館道上"}],"0170056":[{"prefecture":"秋田県","city":"大館市","area":"沼館道南"}],"0170057":[{"prefecture":"秋田県","city":"大館市","area":"沼館"}],"0170862":[{"prefecture":"秋田県","city":"大館市","area":"根下戸"}],"0170864":[{"prefecture":"秋田県","city":"大館市","area":"根下戸新町"}],"0170863":[{"prefecture":"秋田県","city":"大館市","area":"根下戸町"}],"0170842":[{"prefecture":"秋田県","city":"大館市","area":"馬喰町"}],"0170003":[{"prefecture":"秋田県","city":"大館市","area":"橋桁"}],"0170811":[{"prefecture":"秋田県","city":"大館市","area":"八幡"}],"0170823":[{"prefecture":"秋田県","city":"大館市","area":"八幡沢岱"}],"0170005":[{"prefecture":"秋田県","city":"大館市","area":"花岡町"}],"0170803":[{"prefecture":"秋田県","city":"大館市","area":"東台"}],"0170855":[{"prefecture":"秋田県","city":"大館市","area":"櫃崎"}],"0170026":[{"prefecture":"秋田県","city":"大館市","area":"二ツ屋境"}],"0170883":[{"prefecture":"秋田県","city":"大館市","area":"古川町"}],"0170815":[{"prefecture":"秋田県","city":"大館市","area":"部垂町"}],"0170052":[{"prefecture":"秋田県","city":"大館市","area":"松木"}],"0170054":[{"prefecture":"秋田県","city":"大館市","area":"松館"}],"0170051":[{"prefecture":"秋田県","city":"大館市","area":"松峰"}],"0170873":[{"prefecture":"秋田県","city":"大館市","area":"御坂"}],"0170874":[{"prefecture":"秋田県","city":"大館市","area":"美園町"}],"0170868":[{"prefecture":"秋田県","city":"大館市","area":"南神明町"}],"0170828":[{"prefecture":"秋田県","city":"大館市","area":"向町"}],"0170876":[{"prefecture":"秋田県","city":"大館市","area":"餅田"}],"0170827":[{"prefecture":"秋田県","city":"大館市","area":"谷地町"}],"0170826":[{"prefecture":"秋田県","city":"大館市","area":"谷地町後"}],"0170838":[{"prefecture":"秋田県","city":"大館市","area":"山館"}],"0170021":[{"prefecture":"秋田県","city":"大館市","area":"雪沢"}],"0170885":[{"prefecture":"秋田県","city":"大館市","area":"豊町"}],"0170200":[{"prefecture":"秋田県","city":"鹿角郡小坂町","area":""}],"0170204":[{"prefecture":"秋田県","city":"鹿角郡小坂町","area":"荒谷"}],"0170203":[{"prefecture":"秋田県","city":"鹿角郡小坂町","area":"上向"}],"0170201":[{"prefecture":"秋田県","city":"鹿角郡小坂町","area":"小坂"}],"0170202":[{"prefecture":"秋田県","city":"鹿角郡小坂町","area":"小坂鉱山"}],"0170205":[{"prefecture":"秋田県","city":"鹿角郡小坂町","area":"大地"}]}