{"3410000":{"prefecture":"埼玉県","city":"三郷市","area":""},"3410001":{"prefecture":"埼玉県","city":"三郷市","area":"彦糸"},"3410002":{"prefecture":"埼玉県","city":"三郷市","area":"彦音"},"3410003":{"prefecture":"埼玉県","city":"三郷市","area":"彦成"},"3410004":{"prefecture":"埼玉県","city":"三郷市","area":"上彦名"},"3410005":{"prefecture":"埼玉県","city":"三郷市","area":"彦川戸"},"3410006":{"prefecture":"埼玉県","city":"三郷市","area":"上彦川戸"},"3410007":{"prefecture":"埼玉県","city":"三郷市","area":"下彦川戸"},"3410008":{"prefecture":"埼玉県","city":"三郷市","area":"駒形"},"3410009":{"prefecture":"埼玉県","city":"三郷市","area":"新三郷ららシティ"},"3410011":{"prefecture":"埼玉県","city":"三郷市","area":"采女"},"3410012":{"prefecture":"埼玉県","city":"三郷市","area":"半田"},"3410013":{"prefecture":"埼玉県","city":"三郷市","area":"小谷堀"},"3410014":{"prefecture":"埼玉県","city":"三郷市","area":"後谷"},"3410015":{"prefecture":"埼玉県","city":"三郷市","area":"前間"},"3410016":{"prefecture":"埼玉県","city":"三郷市","area":"田中新田"},"3410017":{"prefecture":"埼玉県","city":"三郷市","area":"丹後"},"3410018":{"prefecture":"埼玉県","city":"三郷市","area":"早稲田"},"3410021":{"prefecture":"埼玉県","city":"三郷市","area":"さつき平"},"3410022":{"prefecture":"埼玉県","city":"三郷市","area":"大広戸"},"3410023":{"prefecture":"埼玉県","city":"三郷市","area":"仁蔵"},"3410024":{"prefecture":"埼玉県","city":"三郷市","area":"三郷"},"3410025":{"prefecture":"埼玉県","city":"三郷市","area":"茂田井"},"3410026":{"prefecture":"埼玉県","city":"三郷市","area":"幸房"},"3410027":{"prefecture":"埼玉県","city":"三郷市","area":"笹塚"},"3410028":{"prefecture":"埼玉県","city":"三郷市","area":"南蓮沼"},"3410031":{"prefecture":"埼玉県","city":"三郷市","area":"岩野木"},"3410032":{"prefecture":"埼玉県","city":"三郷市","area":"谷中"},"3410033":{"prefecture":"埼玉県","city":"三郷市","area":"市助"},"3410034":{"prefecture":"埼玉県","city":"三郷市","area":"新和"},"3410035":{"prefecture":"埼玉県","city":"三郷市","area":"鷹野"},"3410036":{"prefecture":"埼玉県","city":"三郷市","area":"東町"},"3410037":{"prefecture":"埼玉県","city":"三郷市","area":"高州"},"3410038":{"prefecture":"埼玉県","city":"三郷市","area":"中央"},"3410041":{"prefecture":"埼玉県","city":"三郷市","area":"花和田"},"3410042":{"prefecture":"埼玉県","city":"三郷市","area":"谷口"},"3410043":{"prefecture":"埼玉県","city":"三郷市","area":"栄"},"3410044":{"prefecture":"埼玉県","city":"三郷市","area":"戸ケ崎"},"3410045":{"prefecture":"埼玉県","city":"三郷市","area":"寄巻"},"3410046":{"prefecture":"埼玉県","city":"三郷市","area":"鎌倉"},"3410050":{"prefecture":"埼玉県","city":"三郷市","area":"ピアラシティ"},"3410051":{"prefecture":"埼玉県","city":"三郷市","area":"天神"},"3410052":{"prefecture":"埼玉県","city":"三郷市","area":"彦野"},"3410053":{"prefecture":"埼玉県","city":"三郷市","area":"彦倉"},"3410054":{"prefecture":"埼玉県","city":"三郷市","area":"泉"},"3410055":{"prefecture":"埼玉県","city":"三郷市","area":"上口"},"3410056":{"prefecture":"埼玉県","city":"三郷市","area":"番匠免"},"3410057":{"prefecture":"埼玉県","city":"三郷市","area":"彦沢"},"3410058":{"prefecture":"埼玉県","city":"三郷市","area":"彦江"},"3410059":{"prefecture":"埼玉県","city":"三郷市","area":"インター南"}}