{"6290101":{"prefecture":"京都府","city":"南丹市","area":"八木町船枝"},"6290102":{"prefecture":"京都府","city":"南丹市","area":"八木町室橋"},"6290103":{"prefecture":"京都府","city":"南丹市","area":"八木町諸畑"},"6290104":{"prefecture":"京都府","city":"南丹市","area":"八木町日置"},"6290111":{"prefecture":"京都府","city":"南丹市","area":"八木町野条"},"6290112":{"prefecture":"京都府","city":"南丹市","area":"八木町池上"},"6290113":{"prefecture":"京都府","city":"南丹市","area":"八木町刑部"},"6290114":{"prefecture":"京都府","city":"南丹市","area":"八木町北廣瀬"},"6290115":{"prefecture":"京都府","city":"南丹市","area":"八木町山室"},"6290121":{"prefecture":"京都府","city":"南丹市","area":"八木町氷所"},"6290122":{"prefecture":"京都府","city":"南丹市","area":"八木町青戸"},"6290131":{"prefecture":"京都府","city":"南丹市","area":"八木町北屋賀"},"6290132":{"prefecture":"京都府","city":"南丹市","area":"八木町屋賀"},"6290133":{"prefecture":"京都府","city":"南丹市","area":"八木町観音寺"},"6290134":{"prefecture":"京都府","city":"南丹市","area":"八木町西田"},"6290141":{"prefecture":"京都府","city":"南丹市","area":"八木町八木"},"6290151":{"prefecture":"京都府","city":"南丹市","area":"八木町南廣瀬"},"6290152":{"prefecture":"京都府","city":"南丹市","area":"八木町大藪"},"6290153":{"prefecture":"京都府","city":"南丹市","area":"八木町八木嶋"},"6290154":{"prefecture":"京都府","city":"南丹市","area":"八木町柴山"},"6290161":{"prefecture":"京都府","city":"南丹市","area":"八木町美里"},"6290162":{"prefecture":"京都府","city":"南丹市","area":"八木町鳥羽"},"6290163":{"prefecture":"京都府","city":"南丹市","area":"八木町玉ノ井"},"6290164":{"prefecture":"京都府","city":"南丹市","area":"八木町池ノ内"},"6290165":{"prefecture":"京都府","city":"南丹市","area":"八木町木原"},"6290166":{"prefecture":"京都府","city":"南丹市","area":"八木町室河原"},"6290271":{"prefecture":"京都府","city":"南丹市","area":"八木町神吉"},"6290301":{"prefecture":"京都府","city":"南丹市","area":"日吉町保野田"},"6290302":{"prefecture":"京都府","city":"南丹市","area":"日吉町志和賀"},"6290311":{"prefecture":"京都府","city":"南丹市","area":"日吉町胡麻"},"6290312":{"prefecture":"京都府","city":"南丹市","area":"日吉町上胡麻"},"6290313":{"prefecture":"京都府","city":"南丹市","area":"日吉町畑郷"},"6290321":{"prefecture":"京都府","city":"南丹市","area":"日吉町佐々江"},"6290322":{"prefecture":"京都府","city":"南丹市","area":"日吉町四ツ谷"},"6290323":{"prefecture":"京都府","city":"南丹市","area":"日吉町田原"},"6290331":{"prefecture":"京都府","city":"南丹市","area":"日吉町生畑"},"6290332":{"prefecture":"京都府","city":"南丹市","area":"日吉町木住"},"6290333":{"prefecture":"京都府","city":"南丹市","area":"日吉町中世木"},"6290334":{"prefecture":"京都府","city":"南丹市","area":"日吉町天若"},"6290335":{"prefecture":"京都府","city":"南丹市","area":"日吉町中"},"6290341":{"prefecture":"京都府","city":"南丹市","area":"日吉町殿田"},"6291101":{"prefecture":"京都府","city":"船井郡京丹波町","area":"仏主"},"6291102":{"prefecture":"京都府","city":"船井郡京丹波町","area":"上乙見"},"6291103":{"prefecture":"京都府","city":"船井郡京丹波町","area":"下乙見"},"6291104":{"prefecture":"京都府","city":"船井郡京丹波町","area":"篠原"},"6291105":{"prefecture":"京都府","city":"船井郡京丹波町","area":"下粟野"},"6291106":{"prefecture":"京都府","city":"船井郡京丹波町","area":"細谷"},"6291107":{"prefecture":"京都府","city":"船井郡京丹波町","area":"西河内"},"6291108":{"prefecture":"京都府","city":"船井郡京丹波町","area":"上粟野"},"6291111":{"prefecture":"京都府","city":"船井郡京丹波町","area":"大迫"},"6291112":{"prefecture":"京都府","city":"船井郡京丹波町","area":"塩谷"},"6291113":{"prefecture":"京都府","city":"船井郡京丹波町","area":"長瀬"},"6291114":{"prefecture":"京都府","city":"船井郡京丹波町","area":"升谷"},"6291115":{"prefecture":"京都府","city":"船井郡京丹波町","area":"中山"},"6291116":{"prefecture":"京都府","city":"船井郡京丹波町","area":"市場"},"6291117":{"prefecture":"京都府","city":"船井郡京丹波町","area":"大倉"},"6291121":{"prefecture":"京都府","city":"船井郡京丹波町","area":"本庄"},"6291122":{"prefecture":"京都府","city":"船井郡京丹波町","area":"小畑"},"6291131":{"prefecture":"京都府","city":"船井郡京丹波町","area":"坂原"},"6291132":{"prefecture":"京都府","city":"船井郡京丹波町","area":"中"},"6291133":{"prefecture":"京都府","city":"船井郡京丹波町","area":"角"},"6291134":{"prefecture":"京都府","city":"船井郡京丹波町","area":"広瀬"},"6291135":{"prefecture":"京都府","city":"船井郡京丹波町","area":"才原"},"6291141":{"prefecture":"京都府","city":"船井郡京丹波町","area":"安栖里"},"6291142":{"prefecture":"京都府","city":"船井郡京丹波町","area":"稲次"},"6291143":{"prefecture":"京都府","city":"船井郡京丹波町","area":"出野"},"6291144":{"prefecture":"京都府","city":"船井郡京丹波町","area":"広野"},"6291145":{"prefecture":"京都府","city":"船井郡京丹波町","area":"大簾"},"6291241":{"prefecture":"京都府","city":"綾部市","area":"井根町"},"6291242":{"prefecture":"京都府","city":"綾部市","area":"十倉名畑町"},"6291243":{"prefecture":"京都府","city":"綾部市","area":"十倉向町"},"6291244":{"prefecture":"京都府","city":"綾部市","area":"十倉中町"},"6291245":{"prefecture":"京都府","city":"綾部市","area":"十倉志茂町"},"6291251":{"prefecture":"京都府","city":"綾部市","area":"忠町"},"6291252":{"prefecture":"京都府","city":"綾部市","area":"佃町"},"6291253":{"prefecture":"京都府","city":"綾部市","area":"武吉町"},"6291254":{"prefecture":"京都府","city":"綾部市","area":"釜輪町"},"6291255":{"prefecture":"京都府","city":"綾部市","area":"戸奈瀬町"},"6291256":{"prefecture":"京都府","city":"綾部市","area":"広瀬町"},"6291257":{"prefecture":"京都府","city":"綾部市","area":"橋上町"},"6291261":{"prefecture":"京都府","city":"綾部市","area":"旭町"},"6291262":{"prefecture":"京都府","city":"綾部市","area":"東山町"},"6291263":{"prefecture":"京都府","city":"綾部市","area":"鷹栖町"},"6291264":{"prefecture":"京都府","city":"綾部市","area":"西原町"},"6291271":{"prefecture":"京都府","city":"綾部市","area":"上原町"},"6291272":{"prefecture":"京都府","city":"綾部市","area":"下替地町"},"6291273":{"prefecture":"京都府","city":"綾部市","area":"下原町"},"6291274":{"prefecture":"京都府","city":"綾部市","area":"和木町"},"6291301":{"prefecture":"京都府","city":"福知山市","area":"夜久野町畑"},"6291302":{"prefecture":"京都府","city":"福知山市","area":"夜久野町今西中"},"6291303":{"prefecture":"京都府","city":"福知山市","area":"夜久野町井田"},"6291304":{"prefecture":"京都府","city":"福知山市","area":"夜久野町額田"},"6291305":{"prefecture":"京都府","city":"福知山市","area":"夜久野町千原"},"6291311":{"prefecture":"京都府","city":"福知山市","area":"夜久野町日置"},"6291312":{"prefecture":"京都府","city":"福知山市","area":"夜久野町末"},"6291313":{"prefecture":"京都府","city":"福知山市","area":"夜久野町高内"},"6291314":{"prefecture":"京都府","city":"福知山市","area":"夜久野町小倉"},"6291315":{"prefecture":"京都府","city":"福知山市","area":"夜久野町大油子"},"6291321":{"prefecture":"京都府","city":"福知山市","area":"夜久野町直見"},"6291322":{"prefecture":"京都府","city":"福知山市","area":"夜久野町平野"},"6291323":{"prefecture":"京都府","city":"福知山市","area":"夜久野町板生"},"6292200":{"prefecture":"京都府","city":"与謝郡与謝野町","area":""},"6292231":{"prefecture":"京都府","city":"宮津市","area":"小松"},"6292232":{"prefecture":"京都府","city":"宮津市","area":"中野"},"6292233":{"prefecture":"京都府","city":"宮津市","area":"溝尻"},"6292234":{"prefecture":"京都府","city":"宮津市","area":"国分"},"6292241":{"prefecture":"京都府","city":"宮津市","area":"成相寺"},"6292242":{"prefecture":"京都府","city":"宮津市","area":"大垣"},"6292243":{"prefecture":"京都府","city":"宮津市","area":"難波野"},"6292244":{"prefecture":"京都府","city":"宮津市","area":"江尻"},"6292251":{"prefecture":"京都府","city":"宮津市","area":"須津"},"6292261":{"prefecture":"京都府","city":"与謝郡与謝野町","area":"男山"},"6292262":{"prefecture":"京都府","city":"与謝郡与謝野町","area":"岩滝"},"6292263":{"prefecture":"京都府","city":"与謝郡与謝野町","area":"弓木"},"6292301":{"prefecture":"京都府","city":"与謝郡与謝野町","area":"上山田"},"6292302":{"prefecture":"京都府","city":"与謝郡与謝野町","area":"下山田"},"6292303":{"prefecture":"京都府","city":"与謝郡与謝野町","area":"石川"},"6292311":{"prefecture":"京都府","city":"与謝郡与謝野町","area":"幾地"},"6292312":{"prefecture":"京都府","city":"与謝郡与謝野町","area":"四辻"},"6292313":{"prefecture":"京都府","city":"与謝郡与謝野町","area":"三河内"},"6292314":{"prefecture":"京都府","city":"与謝郡与謝野町","area":"岩屋"},"6292401":{"prefecture":"京都府","city":"与謝郡与謝野町","area":"加悦奥"},"6292402":{"prefecture":"京都府","city":"与謝郡与謝野町","area":"算所"},"6292403":{"prefecture":"京都府","city":"与謝郡与謝野町","area":"加悦"},"6292404":{"prefecture":"京都府","city":"与謝郡与謝野町","area":"後野"},"6292411":{"prefecture":"京都府","city":"与謝郡与謝野町","area":"明石"},"6292412":{"prefecture":"京都府","city":"与謝郡与謝野町","area":"香河"},"6292413":{"prefecture":"京都府","city":"与謝郡与謝野町","area":"温江"},"6292421":{"prefecture":"京都府","city":"与謝郡与謝野町","area":"金屋"},"6292422":{"prefecture":"京都府","city":"与謝郡与謝野町","area":"滝"},"6292423":{"prefecture":"京都府","city":"与謝郡与謝野町","area":"与謝"},"6292501":{"prefecture":"京都府","city":"京丹後市","area":"大宮町口大野"},"6292502":{"prefecture":"京都府","city":"京丹後市","area":"大宮町河辺"},"6292503":{"prefecture":"京都府","city":"京丹後市","area":"大宮町周枳"},"6292504":{"prefecture":"京都府","city":"京丹後市","area":"大宮町善王寺"},"6292511":{"prefecture":"京都府","city":"京丹後市","area":"大宮町久住"},"6292512":{"prefecture":"京都府","city":"京丹後市","area":"大宮町五十河"},"6292513":{"prefecture":"京都府","city":"京丹後市","area":"大宮町延利"},"6292514":{"prefecture":"京都府","city":"京丹後市","area":"大宮町明田"},"6292515":{"prefecture":"京都府","city":"京丹後市","area":"大宮町新宮"},"6292521":{"prefecture":"京都府","city":"京丹後市","area":"大宮町森本"},"6292522":{"prefecture":"京都府","city":"京丹後市","area":"大宮町三重"},"6292523":{"prefecture":"京都府","city":"京丹後市","area":"大宮町三坂"},"6292531":{"prefecture":"京都府","city":"京丹後市","area":"大宮町奥大野"},"6292532":{"prefecture":"京都府","city":"京丹後市","area":"大宮町谷内"},"6292533":{"prefecture":"京都府","city":"京丹後市","area":"大宮町上常吉"},"6292534":{"prefecture":"京都府","city":"京丹後市","area":"大宮町下常吉"},"6293101":{"prefecture":"京都府","city":"京丹後市","area":"網野町網野"},"6293102":{"prefecture":"京都府","city":"京丹後市","area":"網野町下岡"},"6293103":{"prefecture":"京都府","city":"京丹後市","area":"網野町磯"},"6293104":{"prefecture":"京都府","city":"京丹後市","area":"網野町浅茂川"},"6293111":{"prefecture":"京都府","city":"京丹後市","area":"網野町三津"},"6293112":{"prefecture":"京都府","city":"京丹後市","area":"網野町掛津"},"6293113":{"prefecture":"京都府","city":"京丹後市","area":"網野町小浜"},"6293121":{"prefecture":"京都府","city":"京丹後市","area":"網野町島津"},"6293122":{"prefecture":"京都府","city":"京丹後市","area":"網野町仲禅寺"},"6293131":{"prefecture":"京都府","city":"京丹後市","area":"網野町高橋"},"6293132":{"prefecture":"京都府","city":"京丹後市","area":"網野町公庄"},"6293133":{"prefecture":"京都府","city":"京丹後市","area":"網野町郷"},"6293134":{"prefecture":"京都府","city":"京丹後市","area":"網野町生野内"},"6293135":{"prefecture":"京都府","city":"京丹後市","area":"網野町切畑"},"6293136":{"prefecture":"京都府","city":"京丹後市","area":"網野町新庄"},"6293241":{"prefecture":"京都府","city":"京丹後市","area":"網野町木津"},"6293242":{"prefecture":"京都府","city":"京丹後市","area":"網野町日和田"},"6293243":{"prefecture":"京都府","city":"京丹後市","area":"網野町溝野"},"6293244":{"prefecture":"京都府","city":"京丹後市","area":"網野町俵野"},"6293245":{"prefecture":"京都府","city":"京丹後市","area":"網野町浜詰"},"6293246":{"prefecture":"京都府","city":"京丹後市","area":"網野町塩江"},"6293401":{"prefecture":"京都府","city":"京丹後市","area":"久美浜町十楽"},"6293402":{"prefecture":"京都府","city":"京丹後市","area":"久美浜町仲町"},"6293403":{"prefecture":"京都府","city":"京丹後市","area":"久美浜町向町"},"6293404":{"prefecture":"京都府","city":"京丹後市","area":"久美浜町土居"},"6293405":{"prefecture":"京都府","city":"京丹後市","area":"久美浜町栄町"},"6293406":{"prefecture":"京都府","city":"京丹後市","area":"久美浜町東本町"},"6293407":{"prefecture":"京都府","city":"京丹後市","area":"久美浜町新橋"},"6293408":{"prefecture":"京都府","city":"京丹後市","area":"久美浜町新町"},"6293409":{"prefecture":"京都府","city":"京丹後市","area":"久美浜町西本町"},"6293410":{"prefecture":"京都府","city":"京丹後市","area":"久美浜町"},"6293411":{"prefecture":"京都府","city":"京丹後市","area":"久美浜町栃谷"},"6293412":{"prefecture":"京都府","city":"京丹後市","area":"久美浜町三谷"},"6293413":{"prefecture":"京都府","city":"京丹後市","area":"久美浜町口馬地"},"6293414":{"prefecture":"京都府","city":"京丹後市","area":"久美浜町奥馬地"},"6293415":{"prefecture":"京都府","city":"京丹後市","area":"久美浜町河梨"},"6293416":{"prefecture":"京都府","city":"京丹後市","area":"久美浜町神谷"},"6293421":{"prefecture":"京都府","city":"京丹後市","area":"久美浜町葛野"},"6293422":{"prefecture":"京都府","city":"京丹後市","area":"久美浜町湊宮"},"6293423":{"prefecture":"京都府","city":"京丹後市","area":"久美浜町大向"},"6293424":{"prefecture":"京都府","city":"京丹後市","area":"久美浜町蒲井"},"6293431":{"prefecture":"京都府","city":"京丹後市","area":"久美浜町鹿野"},"6293432":{"prefecture":"京都府","city":"京丹後市","area":"久美浜町平田"},"6293433":{"prefecture":"京都府","city":"京丹後市","area":"久美浜町三分"},"6293434":{"prefecture":"京都府","city":"京丹後市","area":"久美浜町三原"},"6293435":{"prefecture":"京都府","city":"京丹後市","area":"久美浜町壱分"},"6293436":{"prefecture":"京都府","city":"京丹後市","area":"久美浜町大井"},"6293437":{"prefecture":"京都府","city":"京丹後市","area":"久美浜町関"},"6293438":{"prefecture":"京都府","city":"京丹後市","area":"久美浜町長柄"},"6293441":{"prefecture":"京都府","city":"京丹後市","area":"久美浜町神崎"},"6293442":{"prefecture":"京都府","city":"京丹後市","area":"久美浜町甲山"},"6293443":{"prefecture":"京都府","city":"京丹後市","area":"久美浜町海士"},"6293444":{"prefecture":"京都府","city":"京丹後市","area":"久美浜町橋爪"},"6293445":{"prefecture":"京都府","city":"京丹後市","area":"久美浜町島"},"6293446":{"prefecture":"京都府","city":"京丹後市","area":"久美浜町品田"},"6293447":{"prefecture":"京都府","city":"京丹後市","area":"久美浜町友重"},"6293448":{"prefecture":"京都府","city":"京丹後市","area":"久美浜町坂井"},"6293449":{"prefecture":"京都府","city":"京丹後市","area":"久美浜町油池"},"6293551":{"prefecture":"京都府","city":"京丹後市","area":"久美浜町永留"},"6293552":{"prefecture":"京都府","city":"京丹後市","area":"久美浜町女布"},"6293553":{"prefecture":"京都府","city":"京丹後市","area":"久美浜町長野"},"6293554":{"prefecture":"京都府","city":"京丹後市","area":"久美浜町坂谷"},"6293555":{"prefecture":"京都府","city":"京丹後市","area":"久美浜町円頓寺"},"6293556":{"prefecture":"京都府","city":"京丹後市","area":"久美浜町郷"},"6293557":{"prefecture":"京都府","city":"京丹後市","area":"久美浜町竹藤"},"6293558":{"prefecture":"京都府","city":"京丹後市","area":"久美浜町丸山"},"6293559":{"prefecture":"京都府","city":"京丹後市","area":"久美浜町谷"},"6293561":{"prefecture":"京都府","city":"京丹後市","area":"久美浜町野中"},"6293562":{"prefecture":"京都府","city":"京丹後市","area":"久美浜町佐野"},"6293563":{"prefecture":"京都府","city":"京丹後市","area":"久美浜町二俣"},"6293564":{"prefecture":"京都府","city":"京丹後市","area":"久美浜町尉ケ畑"},"6293565":{"prefecture":"京都府","city":"京丹後市","area":"久美浜町小桑"},"6293566":{"prefecture":"京都府","city":"京丹後市","area":"久美浜町安養寺"},"6293570":{"prefecture":"京都府","city":"京丹後市","area":"久美浜町新庄"},"6293571":{"prefecture":"京都府","city":"京丹後市","area":"久美浜町芦原"},"6293572":{"prefecture":"京都府","city":"京丹後市","area":"久美浜町新谷"},"6293573":{"prefecture":"京都府","city":"京丹後市","area":"久美浜町出角"},"6293574":{"prefecture":"京都府","city":"京丹後市","area":"久美浜町市場"},"6293575":{"prefecture":"京都府","city":"京丹後市","area":"久美浜町金谷"},"6293576":{"prefecture":"京都府","city":"京丹後市","area":"久美浜町市野々"},"6293577":{"prefecture":"京都府","city":"京丹後市","area":"久美浜町布袋野"},"6293578":{"prefecture":"京都府","city":"京丹後市","area":"久美浜町畑"},"6293579":{"prefecture":"京都府","city":"京丹後市","area":"久美浜町須田"}}